toobuk/__init__.py
toobuk/__version__.py
toobuk/conf.py
toobuk/connector.py
toobuk/connector_v1.py
toobuk/tlogger.py
toobuk/util.py
toobuk/pattern/__init__.py
toobuk/pattern/abstract.py
toobuk/pattern/list.py
toobuk/pattern/single.py
toobuk-1.0.dist-info/METADATA
toobuk-1.0.dist-info/WHEEL
toobuk-1.0.dist-info/top_level.txt
toobuk-1.0.dist-info/RECORD
