Metadata-Version: 2.1
Name: toobuk
Version: 1.0
Summary: 웹크롤링을 도와줍니다.
Home-page: https://github.com/ramoi/toobuk
Author: mklee
Author-email: ramoi@daum.net
License: MIT
